yuDebug.py
yuDebug/__init__.py
yuDebug/yuDebug.py
yuDebug-1.0.2.dist-info/LICENSE
yuDebug-1.0.2.dist-info/METADATA
yuDebug-1.0.2.dist-info/WHEEL
yuDebug-1.0.2.dist-info/top_level.txt
yuDebug-1.0.2.dist-info/RECORD
