Metadata-Version: 2.1
Name: yuDebug
Version: 1.0.2
Summary: The package provides a more direct way to help students ask their questions about the errors in their codes by combining the codes and the errors to one file.
Home-page: https://github.com/pkmq24/yuDebug
Author: puluterYu
Author-email: pkmq24@qq.com
License: UNKNOWN
Platform: UNKNOWN
Classifier: Programming Language :: Python :: 3
Classifier: License :: OSI Approved :: MIT License
Classifier: Operating System :: OS Independent
Requires-Python: >=3.6
